physcis/__init__.py
physcis/employee.py
physcis/sub/__init__.py
physcis/sub/contractor.py
dummy_common-1.0.0.dist-info/METADATA
dummy_common-1.0.0.dist-info/WHEEL
dummy_common-1.0.0.dist-info/top_level.txt
dummy_common-1.0.0.dist-info/RECORD
