Metadata-Version: 2.1
Name: dummy-common
Version: 1.0.0
Summary: This is the first module for testing
Author: author@email.com
